haveibeenpwnd/__init__.py
haveibeenpwnd/main.py
haveibeenpwnd-0.2.1.dist-info/DESCRIPTION.rst
haveibeenpwnd-0.2.1.dist-info/METADATA
haveibeenpwnd-0.2.1.dist-info/RECORD
haveibeenpwnd-0.2.1.dist-info/WHEEL
haveibeenpwnd-0.2.1.dist-info/entry_points.txt
haveibeenpwnd-0.2.1.dist-info/metadata.json
haveibeenpwnd-0.2.1.dist-info/pbr.json
haveibeenpwnd-0.2.1.dist-info/top_level.txt
